OpenSSL-stubs/METADATA.toml
OpenSSL-stubs/__init__.pyi
OpenSSL-stubs/crypto.pyi
types_openssl_python-0.1.2.dist-info/METADATA
types_openssl_python-0.1.2.dist-info/WHEEL
types_openssl_python-0.1.2.dist-info/top_level.txt
types_openssl_python-0.1.2.dist-info/RECORD
