Metadata-Version: 2.1
Name: types-openssl-python
Version: 0.1.2
Summary: Typing stubs for openssl-python
Home-page: https://github.com/python/typeshed
License: UNKNOWN
Platform: UNKNOWN
Classifier: Typing :: Typed
Requires-Dist: types-cryptography
